mystreamlit-1.7.0.data/scripts/streamlit.cmd
streamlit/__init__.py
streamlit/__main__.py
streamlit/app_session.py
streamlit/beta_util.py
streamlit/bootstrap.py
streamlit/case_converters.py
streamlit/cli.py
streamlit/code_util.py
streamlit/config.py
streamlit/config_option.py
streamlit/config_util.py
streamlit/credentials.py
streamlit/cursor.py
streamlit/delta_generator.py
streamlit/development.py
streamlit/echo.py
streamlit/env_util.py
streamlit/error_util.py
streamlit/errors.py
streamlit/file_util.py
streamlit/folder_black_list.py
streamlit/forward_msg_cache.py
streamlit/forward_msg_queue.py
streamlit/git_util.py
streamlit/in_memory_file_manager.py
streamlit/js_number.py
streamlit/logger.py
streamlit/magic.py
streamlit/metrics_util.py
streamlit/net_util.py
streamlit/script_request_queue.py
streamlit/script_run_context.py
streamlit/script_runner.py
streamlit/secrets.py
streamlit/session_data.py
streamlit/source_util.py
streamlit/stats.py
streamlit/string_util.py
streamlit/temporary_directory.py
streamlit/type_util.py
streamlit/uploaded_file_manager.py
streamlit/url_util.py
streamlit/util.py
streamlit/version.py
streamlit/caching/__init__.py
streamlit/caching/cache_errors.py
streamlit/caching/cache_utils.py
streamlit/caching/hashing.py
streamlit/caching/memo_decorator.py
streamlit/caching/singleton_decorator.py
streamlit/commands/__init__.py
streamlit/commands/page_config.py
streamlit/components/__init__.py
streamlit/components/v1/__init__.py
streamlit/components/v1/component_arrow.py
streamlit/components/v1/components.py
streamlit/elements/__init__.py
streamlit/elements/alert.py
streamlit/elements/arrow.py
streamlit/elements/arrow_altair.py
streamlit/elements/arrow_vega_lite.py
streamlit/elements/balloons.py
streamlit/elements/bokeh_chart.py
streamlit/elements/button.py
streamlit/elements/camera_input.py
streamlit/elements/checkbox.py
streamlit/elements/color_picker.py
streamlit/elements/dataframe_selector.py
streamlit/elements/deck_gl_json_chart.py
mystreamlit-1.7.0.dist-info/METADATA
mystreamlit-1.7.0.dist-info/WHEEL
mystreamlit-1.7.0.dist-info/entry_points.txt
mystreamlit-1.7.0.dist-info/top_level.txt
mystreamlit-1.7.0.dist-info/RECORD
